underpy/__init__.py
underpy/encapsulation.py
underpy/mutability.py
underpy/service.py
underpy/typing.py
underpyx-0.1.1.dist-info/licenses/LICENSE
underpyx-0.1.1.dist-info/METADATA
underpyx-0.1.1.dist-info/WHEEL
underpyx-0.1.1.dist-info/top_level.txt
underpyx-0.1.1.dist-info/RECORD
