Metadata-Version: 2.4
Name: underpyx
Version: 0.1.1
Summary: Fundamental utilities in python, such as encapsulation, immutability, service patterns, and JSON type hinting.
Author-email: Ariana Maghsoudi <ariana.maghsoudi82@gmail.com>
License: MIT
Requires-Python: >=3.8
License-File: LICENSE
Provides-Extra: dev
Requires-Dist: pytest; extra == "dev"
Requires-Dist: assertpy; extra == "dev"
Dynamic: license-file
